__init__.py
hekian.py
utils.py
hekian-0.1.0.dist-info/METADATA
hekian-0.1.0.dist-info/WHEEL
hekian-0.1.0.dist-info/top_level.txt
hekian-0.1.0.dist-info/RECORD
