Metadata-Version: 2.1
Name: hekian
Version: 0.1.0
Summary: Small library to facilitate test-time-compute!
Requires-Python: >=3.11
